Workbook

Sheet Financial Summary 
A1: Revolut Financial Summary
B2: Metric | C2: FY2022 | D2: FY2023 | E2: FY2024 | F2: FY2025 | G2: FY2026G | H2: Source / note
A3: Black text = straight from reports
A4: Blue text = calculated (formulas) | B4: FX Assumptions (USD per GBP)
A5: Yellow highlight = per project brief | B5: Average Rate | C5: 1.24 | D5: 1.24 | E5: 1.28 | F5: 1.32 | G5: 1.32 | H5: Annual averages of daily GBP/USD (PoundSterlingLive): 2022 1.236, 2023 1.244, 2024 1.278, 2025 1.319. Consistent with Revolut's own USD conversions (FY24 $4.0bn, FY25 $6.0bn).
A6: Red text = assumption
B8: Income Statement (GBP thousands)
B9: Revenue | C9: 922547 | D9: 1797890 | E9: 3090043 | F9: 4515770 | G9: =G20/G5 -> 6818181.8 | H9: Consolidated Statement of Comprehensive Income: FY25 AR p.96, FY24 AR p.80, FY23 AR p.97, FY22 AR p.83.
B10: Revenue growth | D10: =(D$9-C$9)/C$9 -> 0.94883296 | E10: =(E$9-D$9)/D$9 -> 0.71870526 | F10: =(F$9-E$9)/E$9 -> 0.4613939 | G10: =(G$9-F$9)/F$9 -> 0.50986029 | H10: Company reports: FY23 +95%, FY24 +72%, FY25 +46%.
B11: of which interest income | C11: 82689 | D11: 499561 | E11: 790240 | F11: 974159 | H11: Interest income line in the same statements (FY22–FY25 annual reports).
B12: Interest income share of revenue | C12: =C$11/C$9 -> 0.089631206 | D12: =D$11/D$9 -> 0.2778596 | E12: =E$11/E$9 -> 0.25573754 | F12: =F$11/F$9 -> 0.21572379 | H12: Key rate-sensitivity metric. Falls from 28% (FY23) to 22% (FY25).
B13: Profit before tax | C13: -25418 | D13: 437828 | E13: 1088730 | F13: 1713273 | G13: =G22/G5 -> 2651515.2 | H13: FY22 loss of £25.4m per FY22 AR p.83 (tax credit gives £5.8m net profit). FY24 £1.09bn, FY25 £1.71bn per FY25 AR p.96.
B14: PBT margin | C14: =C$13/C$9 -> -0.027551984 | D14: =D$13/D$9 -> 0.24352324 | E14: =E$13/E$9 -> 0.3523349 | F14: =F$13/F$9 -> 0.37939776 | G14: =G$13/G$9 -> 0.38888889 | H14: Company states FY24 35%, FY25 38%.
B15: Net profit | C15: 5802 | D15: 344075 | E15: 790426 | F15: 1304628 | G15: =G13*(1-F17) -> 2019083.3 | H15: FY22 £6m (tax credit despite pretax loss).
B16: Net margin | C16: =C$15/C$9 -> 0.0062891105 | D16: =D$15/D$9 -> 0.19137711 | E16: =E$15/E$9 -> 0.25579773 | F16: =F$15/F$9 -> 0.28890488 | G16: =G15/G9 -> 0.29613222
B17: Effective tax rate | F17: =1-(F15/F13) -> 0.23851715
B18: Revenue growth slowdown factor | E18: =(E10/D10) -> 0.75746237 | F18: =(F10/E10) -> 0.6419793
B19: USD view (USD thousands )
B20: Revenue (USD) | C20: =C$9*C$5 -> 1143958.3 | D20: =D$9*D$5 -> 2229383.6 | E20: =E$9*E$5 -> 3955255 | F20: =F$9*F$5 -> 5960816.4 | G20: 9000000 | H20: Converted at average rate. FY26G = $9bn per brief
B21: Revenue growth (USD) | D21: =D$20/C$20-1 -> 0.94883296 | E21: =E$20/D$20-1 -> 0.77414737 | F21: =F$20/E$20-1 -> 0.50706246 | G21: =G$20/F$20-1 -> 0.50986029
B22: Profit before tax (USD) | C22: =C$13*C$5 -> -31518.32 | D22: =D$13*D$5 -> 542906.72 | E22: =E$13*E$5 -> 1393574.4 | F22: =F$13*F$5 -> 2261520.4 | G22: 3500000 | H22: Converted at average rate. FY26G = $3.5bn per brief
B23: PBT margin (USD) | C23: =C$22/C$20 -> -0.027551984 | D23: =D$22/D$20 -> 0.24352324 | E23: =E$22/E$20 -> 0.3523349 | F23: =F$22/F$20 -> 0.37939776 | G23: =G$22/G$20 -> 0.38888889
B26: Balance Sheet, Customers & Other KPIs
B27: Customer deposits (GBP thousands) | C27: 12556413 | D27: 15115089 | E27: 22345968 | F27: 36142908 | H27: APM "Customer deposits" = on-balance-sheet bank deposits + e-money. FY25 AR p.200 (FY25, FY24); FY23 AR p.190 (FY23, FY22).
B28: Customer deposit growth | D28: =(D$27-C$27)/C$27 -> 0.20377444 | E28: =(E$27-D$27)/D$27 -> 0.47838812 | F28: =(F$27-E$27)/E$27 -> 0.61742414
B29: Total customer balances incl. partner savings (GBP thousands) | C29: 13241365 | D29: 18215513 | E29: 30247824 | F29: 50182946 | H29: Deposits + off-balance-sheet savings with partners / Flexible Cash Funds. FY25 AR p.200; FY24 AR p.172; FY23 AR p.190.
B30: Retail customers (millions) | C30: 26.2 | D30: 38 | E30: 52.5 | F30: 68.3 | H30: FY23 AR highlights (FY22 26.2m, FY23 38.0m); FY25 AR highlights (FY24 52.5m, FY25 68.3m).
B31: Revenue per average retail customer (GBP) | D31: =(D$9/1000)/AVERAGE(C$30,D$30) -> 56.009034 | E31: =(E$9/1000)/AVERAGE(D$30,E$30) -> 68.288243 | F31: =(F$9/1000)/AVERAGE(E$30,F$30) -> 74.764404 | H31: Revenue ÷ average of opening and closing retail customers.
B32: Revenue per customer growth | E32: =E$31/D$31-1 -> 0.21923622 | F32: =F$31/E$31-1 -> 0.094835664
B33: Interest income growth | D33: =(D$11-C$11)/C$11 -> 5.0414444 | E33: =(E$11-D$11)/D$11 -> 0.58186888 | F33: =(F$11-E$11)/E$11 -> 0.23273816 | H33: Compare with total revenue growth (row 10): rate-sensitive income is growing more slowly.

Sheet Peers
B2: as of 9 of October 2026
B3: Company | C3: Market cap ($bn) | D3: Revenue last FY ($bn) | E3: Revenue next FY forecast ($bn) | F3: Revenue growth | G3: Net margin | H3: P/S trailing | I3: P/S forward | J3: P/E forward | L3: Sources
B4: Nubank | C4: 77.9 | D4: 16.3 | E4: 22.8 | F4: =(E4-D4)/D4 -> 0.39877301 | G4: 0.178 | H4: =C4/D4 -> 4.7791411 | I4: =C4/E4 -> 3.4166667 | J4: 16.6 | L4: https://stockanalysis.com/stocks/nu/statistics/ | M4: https://stockanalysis.com/stocks/nu/forecast/
B5: SoFi | C5: 20.4 | D5: 3.58 | E5: 4.88 | F5: =(E5-D5)/D5 -> 0.36312849 | G5: 0.149 | H5: =C5/D5 -> 5.698324 | I5: =C5/E5 -> 4.1803279 | J5: 21.7 | L5: StockAnalysis: SoFi statistics and forecast
B6: Wise | C6: 11.8 | D6: 2.5 | E6: 2.92 | F6: =(E6-D6)/D6 -> 0.168 | G6: 0.199 | H6: =C6/D6 -> 4.72 | I6: =C6/E6 -> 4.0410959 | J6: 19.4 | L6: StockAnalysis: Wise statistics
B7: Robinhood | C7: 98 | D7: 4.47 | E7: 5.28 | F7: =(E7-D7)/D7 -> 0.18120805 | G7: 0.42 | H7: =C7/D7 -> 21.923937 | I7: =C7/E7 -> 18.560606 | J7: 43.2 | L7: StockAnalysis: Robinhood statistics
B8: Peer Minimum | F8: =MIN(F4:F7) -> 0.168 | G8: =MIN(G4:G7) -> 0.149 | H8: =MIN(H4:H7) -> 4.72 | I8: =MIN(I4:I7) -> 3.4166667 | J8: =MIN(J4:J7) -> 16.6
B9: Peer Median | F9: =MEDIAN(F4:F7) -> 0.27216827 | G9: =MEDIAN(G4:G7) -> 0.1885 | H9: =MEDIAN(H4:H7) -> 5.2387326 | I9: =MEDIAN(I4:I7) -> 4.1107119 | J9: =MEDIAN(J4:J7) -> 20.55
B10: Peer Maximum | F10: =MAX(F4:F7) -> 0.39877301 | G10: =MAX(G4:G7) -> 0.42 | H10: =MAX(H4:H7) -> 21.923937 | I10: =MAX(I4:I7) -> 18.560606 | J10: =MAX(J4:J7) -> 43.2
B11: Revolut | C11: 115 | D11: ='Financial Summary '!F20/10^6 -> 5.9608164 | E11: ='Financial Summary '!G20/10^6 -> 9 | F11: ='Financial Summary '!G10 -> 0.50986029 | G11: ='Financial Summary '!F16 -> 0.28890488 | H11: =C11/D11 -> 19.292659 | I11: =C11/E11 -> 12.777778 | J11: =C11/(Projections!I10/10^6) -> 43.148894
B12: Revolut premium vs median | F12: =F11/F9-1 -> 0.87332744 | G12: =G11/G9-1 -> 0.5326519 | H12: =H11/H9-1 -> 2.682696 | I12: =I11/I9-1 -> 2.10841 | J12: =J11/J9-1 -> 1.0997029
B15: Refresh check: market caps at the 16 Oct 2026 close (StockAnalysis). Not linked to the model
B16: Company | C16: Market cap 9 Oct ($bn) | D16: Market cap 16 Oct ($bn) | E16: Change
B17: Nubank | C17: =C4 -> 77.9 | D17: 70.33 | E17: =D17/C17-1 -> -0.097175866
B18: SoFi | C18: =C5 -> 20.4 | D18: 18.79 | E18: =D18/C18-1 -> -0.078921569
B19: Wise | C19: =C6 -> 11.8 | D19: 11.25 | E19: =D19/C19-1 -> -0.046610169
B20: Robinhood | C20: =C7 -> 98 | D20: 88.89 | E20: =D20/C20-1 -> -0.092959184
B21: Median change | E21: =MEDIAN(E17:E20) -> -0.085940376

Sheet Projections
C3: USD based | F3: “A” for actual, “G” for guidance, “E” for estimate
B4: Assumptions | C4: Bull | D4: Base | E4: Bear
B5: Revenue slowdown factor | C5: 0.76 | D5: 0.64 | E5: 0.52 | F5: BULL | H5: FY25A | I5: FY26G | J5: FY27E | K5: FY28E
B6: Growth rate 27' | C6: =C5*'Financial Summary '!G10 -> 0.38749382 | D6: =D5*'Financial Summary '!G10 -> 0.32631059 | E6: =E5*'Financial Summary '!G10 -> 0.26512735 | G6: Revenue | H6: ='Financial Summary '!F20 -> 5960816.4 | I6: ='Financial Summary '!G20 -> 9000000 | J6: =C8 -> 12487444 | K6: =C9 -> 16164938
B7: Growth rate 28' | C7: =C6*C5 -> 0.29449531 | D7: =D6*D5 -> 0.20883878 | E7: =E6*E5 -> 0.13786622 | G7: Growth | J7: =(J6/I6) -1 -> 0.38749382 | K7: =(K6/J6) -1 -> 0.29449531
B8: Revenue 27' | C8: =(1+C6)*'Financial Summary '!G20 -> 12487444 | D8: =(1+D6)*'Financial Summary '!G20 -> 11936795 | E8: =(1+E6)*'Financial Summary '!G20 -> 11386146 | G8: PBT | H8: ='Financial Summary '!F22 -> 2261520.4 | I8: ='Financial Summary '!G22 -> 3500000 | J8: =J6*C10 -> 4994977.8 | K8: =K6*C10 -> 6465975.3
B9: Revenue 28' | C9: =C8*(1+C7) -> 16164938 | D9: =D8*(1+D7) -> 14429661 | E9: =E8*(1+E7) -> 12955911 | G9: PBT Margin | J9: =J8/J6 -> 0.4 | K9: =K8/K6 -> 0.4
B10: PBT Margin | C10: 0.4 | D10: ='Financial Summary '!G14 -> 0.38888889 | E10: 0.33 | G10: Net profit | H10: ='Financial Summary '!F15*'Financial Summary '!F5 -> 1722109 | I10: =I8*(1-C11) -> 2665190 | J10: =J8*(1-C11) -> 3803589.9 | K10: =K8*(1-C11) -> 4923729.2
B11: Effective Tax Rate | C11: ='Financial Summary '!F17 -> 0.23851715 | D11: =C11 -> 0.23851715 | E11: =C11 -> 0.23851715
B12: Exit P/S | C12: =Peers!I11 -> 12.777778 | D12: =AVERAGE(Peers!I9,Peers!I11) -> 8.4442448 | E12: =Peers!I9 -> 4.1107119 | H12: FY25A | I12: FY26G | J12: FY27E | K12: FY28E
B13: Exit P/E | C13: =Peers!J11 -> 43.148894 | D13: =AVERAGE(Peers!J9,Peers!J11) -> 31.849447 | E13: =Peers!J9 -> 20.55 | F13: BASE
B14: Entry Valuation | C14: 115 | G14: Revenue | H14: ='Financial Summary '!F20 -> 5960816.4 | I14: =I6 -> 9000000 | J14: =D8 -> 11936795 | K14: =D9 -> 14429661
G15: Growth | J15: =J14/I14 -1 -> 0.32631059 | K15: =K14/J14 -1 -> 0.20883878
G16: PBT | H16: =H8 -> 2261520.4 | I16: =I8 -> 3500000 | J16: =J14*D10 -> 4642087.1 | K16: =K14*D10 -> 5611534.8
G17: PBT Margin | J17: =J16/J14 -> 0.38888889 | K17: =K16/K14 -> 0.38888889
G18: Net profit | H18: =H10 -> 1722109 | I18: =I10 -> 2665190 | J18: =J16*(1-D11) -> 3534869.7 | K18: =K16*(1-D11) -> 4273087.5
H20: FY25A | I20: FY26G | J20: FY27E | K20: FY28E
F21: BEAR
G22: Revenue | H22: ='Financial Summary '!F20 -> 5960816.4 | I22: =I6 -> 9000000 | J22: =E8 -> 11386146 | K22: =E9 -> 12955911
G23: Growth | J23: =J22/I22 -1 -> 0.26512735 | K23: =K22/J22 -1 -> 0.13786622
G24: PBT | H24: =H8 -> 2261520.4 | I24: =I8 -> 3500000 | J24: =J22*E10 -> 3757428.2 | K24: =K22*E10 -> 4275450.7
G25: PBT Margin | J25: =J24/J22 -> 0.33 | K25: =K24/K22 -> 0.33
G26: Net profit | H26: =H10 -> 1722109 | I26: =I10 -> 2665190 | J26: =J24*(1-E11) -> 2861217.1 | K26: =K24*(1-E11) -> 3255682.4
B28: Exit valuation
B29: Scenario | C29: 2028 revenue | D29: Exit P/S | E29: Value (P/S) | F29: 2028 net profit | G29: Exit P/E | H29: Value (P/E) | I29: Average | J29: vs $115B | K29: Brief’s version
B30: Bull | C30: =K6/10^6 -> 16.164938 | D30: =C12 -> 12.777778 | E30: =C30*D30 -> 206.55199 | F30: =K10/10^6 -> 4.9237292 | G30: =C13 -> 43.148894 | H30: =G30*F30 -> 212.45347 | I30: =AVERAGE(E30,H30) -> 209.50273 | J30: =I30/$C$14 -1 -> 0.82176287 | K30: =C14*1.5 -> 172.5
B31: Base | C31: =K14/10^6 -> 14.429661 | D31: =D12 -> 8.4442448 | E31: =C31*D31 -> 121.84759 | F31: =K18/10^6 -> 4.2730875 | G31: =D13 -> 31.849447 | H31: =G31*F31 -> 136.09548 | I31: =AVERAGE(E31,H31) -> 128.97153 | J31: =I31/$C$14 -1 -> 0.12149159 | K31: =C14 -> 115
B32: Bear | C32: =K22/10^6 -> 12.955911 | D32: =E12 -> 4.1107119 | E32: =C32*D32 -> 53.258018 | F32: =K26/10^6 -> 3.2556823 | G32: =E13 -> 20.55 | H32: =G32*F32 -> 66.904272 | I32: =AVERAGE(E32,H32) -> 60.081145 | J32: =I32/$C$14 -1 -> -0.47755526 | K32: =C14*0.7 -> 80.5

Sheet Returns 
B3: Inputs
B4: Entry Valuation (bln) | C4: =115 -> 115
B5: Investment (mln) | C5: 15
B6: Holding period (years) | C6: 2.5
B7: Target IRR (low) | C7: 0.2
B8: Target IRR (high) | C8: 0.25
B9: Target MOIC (low) | C9: =(1+C7)^C6 -> 1.577441
B10: Target MOIC (high) | C10: =(1+C8)^C6 -> 1.7469281
B11: Brief hold period (years) | C11: 2
E17: Source: https://equidam.com/resources/equidam-vc-method-paper.pdf
B19: Scenario | C19: Exit Value bln | D19: MOIC | E19: Proceeds mln | F19: Profit | G19: IRR | H19: Meets target? | I19: Probability
B20: Bull | C20: =Projections!I30 -> 209.50273 | D20: =C20/$C$4 -> 1.8217629 | E20: =D20*$C$5 -> 27.326443 | F20: =E20-C5 -> 12.326443 | G20: =D20^(1/$C$6)-1 -> 0.27114982 | H20: =IF(G20>=$C$7,"YES","NO") -> YES | I20: 0.25
B21: Base | C21: =Projections!I31 -> 128.97153 | D21: =C21/$C$4 -> 1.1214916 | E21: =D21*$C$5 -> 16.822374 | F21: =E21-C5 -> 1.8223738 | G21: =D21^(1/$C$6)-1 -> 0.046931841 | H21: =IF(G21>=$C$7,"YES","NO") -> NO | I21: 0.5
B22: Bear | C22: =Projections!I32 -> 60.081145 | D22: =C22/$C$4 -> 0.52244474 | E22: =D22*$C$5 -> 7.8366711 | F22: =E22-C5 -> -7.1633289 | G22: =D22^(1/$C$6)-1 -> -0.22871276 | H22: =IF(G22>=$C$7,"YES","NO") -> NO | I22: 0.25
B23: Expected | C23: =SUMPRODUCT(C20:C22,I20:I22) -> 131.88174 | D23: =C23/$C$4 -> 1.1467977 | G23: =D23^(1/$C$6)-1 -> 0.056318108 | H23: =IF(G23>=$C$7,"YES","NO") -> NO
B26: Brief's rule-based scenarios (exit = $115B × brief multiplier, from Projections K30:K32)
B27: Scenario | C27: Exit Value bln | D27: MOIC | E27: Proceeds mln | F27: Profit | G27: IRR (brief hold) | H27: IRR (model hold) | I27: Meets target? (brief hold)
B28: Bull (+50%) | C28: =Projections!K30 -> 172.5 | D28: =C28/$C$4 -> 1.5 | E28: =D28*$C$5 -> 22.5 | F28: =E28-$C$5 -> 7.5 | G28: =D28^(1/$C$11)-1 -> 0.22474487 | H28: =D28^(1/$C$6)-1 -> 0.17607902 | I28: =IF(G28>=$C$7,"YES","NO") -> YES
B29: Base (flat) | C29: =Projections!K31 -> 115 | D29: =C29/$C$4 -> 1 | E29: =D29*$C$5 -> 15 | F29: =E29-$C$5 -> 0 | G29: =D29^(1/$C$11)-1 -> 0 | H29: =D29^(1/$C$6)-1 -> 0 | I29: =IF(G29>=$C$7,"YES","NO") -> NO
B30: Bear (−30%) | C30: =Projections!K32 -> 80.5 | D30: =C30/$C$4 -> 0.7 | E30: =D30*$C$5 -> 10.5 | F30: =E30-$C$5 -> -4.5 | G30: =D30^(1/$C$11)-1 -> -0.16333997 | H30: =D30^(1/$C$6)-1 -> -0.13295984 | I30: =IF(G30>=$C$7,"YES","NO") -> NO
B33: Management-anchored scenarios (CEO's reported IPO target of $150–200B, FT, Apr 2026)
B34: Scenario | C34: Exit Value bln | D34: MOIC | E34: Proceeds mln | F34: Profit | G34: IRR (brief hold) | H34: IRR (model hold) | I34: Meets target? (model hold)
B35: CEO low | C35: 150 | D35: =C35/$C$4 -> 1.3043478 | E35: =D35*$C$5 -> 19.565217 | F35: =E35-$C$5 -> 4.5652174 | G35: =D35^(1/$C$11)-1 -> 0.14208048 | H35: =D35^(1/$C$6)-1 -> 0.11213464 | I35: =IF(H35>=$C$7,"YES","NO") -> NO
B36: CEO mid | C36: =AVERAGE(C35,C37) -> 175 | D36: =C36/$C$4 -> 1.5217391 | E36: =D36*$C$5 -> 22.826087 | F36: =E36-$C$5 -> 7.826087 | G36: =D36^(1/$C$11)-1 -> 0.23358791 | H36: =D36^(1/$C$6)-1 -> 0.18286746 | I36: =IF(H36>=$C$7,"YES","NO") -> NO
B37: CEO high | C37: 200 | D37: =C37/$C$4 -> 1.7391304 | E37: =D37*$C$5 -> 26.086957 | F37: =E37-$C$5 -> 11.086957 | G37: =D37^(1/$C$11)-1 -> 0.31876095 | H37: =D37^(1/$C$6)-1 -> 0.24776518 | I37: =IF(H37>=$C$7,"YES","NO") -> YES
B40: VC method: maximum entry valuation that still delivers the target IRR
B41: Max entry = exit value ÷ (1 + target IRR) ^ hold period. Discount = how far below $115B the entry must be (negative = the target is met even above $115B).
B42: Exit anchor | C42: Exit Value bln | D42: Max entry @ low IRR (model hold) | E42: Max entry @ high IRR (model hold) | F42: Max entry @ low IRR (brief hold) | G42: Max entry @ high IRR (brief hold) | H42: Discount needed (low IRR, model hold) | I42: Discount needed (high IRR, model hold)
B43: Model bull | C43: =C20 -> 209.50273 | D43: =C43/(1+$C$7)^$C$6 -> 132.81177 | E43: =C43/(1+$C$8)^$C$6 -> 119.92636 | F43: =C43/(1+$C$7)^$C$11 -> 145.48801 | G43: =C43/(1+$C$8)^$C$11 -> 134.08175 | H43: =1-D43/$C$4 -> -0.15488498 | I43: =1-E43/$C$4 -> -0.042837919
B44: Model base | C44: =C21 -> 128.97153 | D44: =C44/(1+$C$7)^$C$6 -> 81.759974 | E44: =C44/(1+$C$8)^$C$6 -> 73.827613 | F44: =C44/(1+$C$7)^$C$11 -> 89.563564 | G44: =C44/(1+$C$8)^$C$11 -> 82.541781 | H44: =1-D44/$C$4 -> 0.2890437 | I44: =1-E44/$C$4 -> 0.35802075
B45: Model bear | C45: =C22 -> 60.081145 | D45: =C45/(1+$C$7)^$C$6 -> 38.08773 | E45: =C45/(1+$C$8)^$C$6 -> 34.392454 | F45: =C45/(1+$C$7)^$C$11 -> 41.723017 | G45: =C45/(1+$C$8)^$C$11 -> 38.451933 | H45: =1-D45/$C$4 -> 0.66880235 | I45: =1-E45/$C$4 -> 0.70093518
B46: Model expected | C46: =C23 -> 131.88174 | D46: =C46/(1+$C$7)^$C$6 -> 83.604863 | E46: =C46/(1+$C$8)^$C$6 -> 75.49351 | F46: =C46/(1+$C$7)^$C$11 -> 91.584538 | G46: =C46/(1+$C$8)^$C$11 -> 84.404311 | H46: =1-D46/$C$4 -> 0.27300119 | I46: =1-E46/$C$4 -> 0.34353469
B47: Brief bull (+50%) | C47: =C28 -> 172.5 | D47: =C47/(1+$C$7)^$C$6 -> 109.35433 | E47: =C47/(1+$C$8)^$C$6 -> 98.744762 | F47: =C47/(1+$C$7)^$C$11 -> 119.79167 | G47: =C47/(1+$C$8)^$C$11 -> 110.4 | H47: =1-D47/$C$4 -> 0.049092782 | I47: =1-E47/$C$4 -> 0.1413499
B48: Brief base (flat) | C48: =C29 -> 115 | D48: =C48/(1+$C$7)^$C$6 -> 72.902887 | E48: =C48/(1+$C$8)^$C$6 -> 65.829841 | F48: =C48/(1+$C$7)^$C$11 -> 79.861111 | G48: =C48/(1+$C$8)^$C$11 -> 73.6 | H48: =1-D48/$C$4 -> 0.36606185 | I48: =1-E48/$C$4 -> 0.4275666
B49: CEO low ($150B) | C49: =C35 -> 150 | D49: =C49/(1+$C$7)^$C$6 -> 95.090722 | E49: =C49/(1+$C$8)^$C$6 -> 85.86501 | F49: =C49/(1+$C$7)^$C$11 -> 104.16667 | G49: =C49/(1+$C$8)^$C$11 -> 96 | H49: =1-D49/$C$4 -> 0.17312416 | I49: =1-E49/$C$4 -> 0.25334774
B50: CEO high ($200B) | C50: =C37 -> 200 | D50: =C50/(1+$C$7)^$C$6 -> 126.78763 | E50: =C50/(1+$C$8)^$C$6 -> 114.48668 | F50: =C50/(1+$C$7)^$C$11 -> 138.88889 | G50: =C50/(1+$C$8)^$C$11 -> 128 | H50: =1-D50/$C$4 -> -0.10250112 | I50: =1-E50/$C$4 -> 0.0044636483
B52: Max entry range, expected case ($bn) | C52: =E46 -> 75.49351 | D52: =D46 -> 83.604863 | E52: ← high-IRR (25%) and low-IRR (20%) bounds over the model hold; this is the "$75–84bn" in the 15 Oct notes

Sheet Sensitivity Table
B1: Sensitivity analysis (USD, $bn)
B3: 1. IRR by entry valuation and hold period
B4: Exit case (pick from list) | C4: Expected | D4: Exit value ($bn) | E4: {=INDEX($M$5:$M$10,MATCH($C$4,$L$5:$L$10,0))} -> 131.88174 | F4: Target IRR (low) | G4: ='Returns '!C7 -> 0.2 | L4: Case | M4: Exit value ($bn)
L5: Bull | M5: ='Returns '!C20 -> 209.50273
B6: Entry valuation ($bn) ↓ / Hold period (years) → | C6: 1.5 | D6: 2 | E6: 2.5 | F6: 3 | L6: Base | M6: ='Returns '!C21 -> 128.97153
B7: 75 | C7: =($E$4/$B7)^(1/C$6)-1 -> 0.45685253 | D7: =($E$4/$B7)^(1/D$6)-1 -> 0.32605548 | E7: =($E$4/$B7)^(1/E$6)-1 -> 0.2532836 | F7: =($E$4/$B7)^(1/F$6)-1 -> 0.20700146 | L7: Bear | M7: ='Returns '!C22 -> 60.081145
B8: 85 | C8: =($E$4/$B8)^(1/C$6)-1 -> 0.34022326 | D8: =($E$4/$B8)^(1/D$6)-1 -> 0.24561223 | E8: =($E$4/$B8)^(1/E$6)-1 -> 0.19208244 | F8: =($E$4/$B8)^(1/F$6)-1 -> 0.15768012 | L8: Expected | M8: ='Returns '!C23 -> 131.88174
B9: 95 | C9: =($E$4/$B9)^(1/C$6)-1 -> 0.2444402 | D9: =($E$4/$B9)^(1/D$6)-1 -> 0.17823121 | E9: =($E$4/$B9)^(1/E$6)-1 -> 0.14020888 | F9: =($E$4/$B9)^(1/F$6)-1 -> 0.1155448 | L9: CEO $150B | M9: ='Returns '!C35 -> 150
B10: 105 | C10: =($E$4/$B10)^(1/C$6)-1 -> 0.16411773 | D10: =($E$4/$B10)^(1/D$6)-1 -> 0.12072143 | E10: =($E$4/$B10)^(1/E$6)-1 -> 0.095464079 | F10: =($E$4/$B10)^(1/F$6)-1 -> 0.078942875 | L10: CEO $200B | M10: ='Returns '!C37 -> 200
B11: 115 | C11: =($E$4/$B11)^(1/C$6)-1 -> 0.095614761 | D11: =($E$4/$B11)^(1/D$6)-1 -> 0.070886408 | E11: =($E$4/$B11)^(1/E$6)-1 -> 0.056318108 | F11: =($E$4/$B11)^(1/F$6)-1 -> 0.04671618
B12: 125 | C12: =($E$4/$B12)^(1/C$6)-1 -> 0.036373803 | D12: =($E$4/$B12)^(1/D$6)-1 -> 0.027158158 | E12: =($E$4/$B12)^(1/E$6)-1 -> 0.021668153 | F12: =($E$4/$B12)^(1/F$6)-1 -> 0.018024461
B13: Simplification: the exit value is held constant across hold periods (a longer hold would in reality mean a later exit on a larger revenue base).
B16: 2. Exit valuation ($bn) by exit P/S multiple and FY2027 revenue
B17: FY27E revenue in our scenarios ($bn): | C17: Bear | D17: =Projections!E8/10^6 -> 11.386146 | E17: Base | F17: =Projections!D8/10^6 -> 11.936795 | G17: Bull | H17: =Projections!C8/10^6 -> 12.487444
B19: FY27 revenue ($bn) ↓ / Exit P/S → | C19: 4 | D19: 6 | E19: 8 | F19: 10 | G19: 12 | H19: 14 | J19: Entry valuation ($bn) | K19: ='Returns '!C4 -> 115
B20: 10.5 | C20: =$B20*C$19 -> 42 | D20: =$B20*D$19 -> 63 | E20: =$B20*E$19 -> 84 | F20: =$B20*F$19 -> 105 | G20: =$B20*G$19 -> 126 | H20: =$B20*H$19 -> 147 | J20: Exit needed for target IRR ($bn) | K20: ='Returns '!C4*'Returns '!C9 -> 181.40571
B21: 11 | C21: =$B21*C$19 -> 44 | D21: =$B21*D$19 -> 66 | E21: =$B21*E$19 -> 88 | F21: =$B21*F$19 -> 110 | G21: =$B21*G$19 -> 132 | H21: =$B21*H$19 -> 154
B22: 11.5 | C22: =$B22*C$19 -> 46 | D22: =$B22*D$19 -> 69 | E22: =$B22*E$19 -> 92 | F22: =$B22*F$19 -> 115 | G22: =$B22*G$19 -> 138 | H22: =$B22*H$19 -> 161
B23: 12 | C23: =$B23*C$19 -> 48 | D23: =$B23*D$19 -> 72 | E23: =$B23*E$19 -> 96 | F23: =$B23*F$19 -> 120 | G23: =$B23*G$19 -> 144 | H23: =$B23*H$19 -> 168
B24: 12.5 | C24: =$B24*C$19 -> 50 | D24: =$B24*D$19 -> 75 | E24: =$B24*E$19 -> 100 | F24: =$B24*F$19 -> 125 | G24: =$B24*G$19 -> 150 | H24: =$B24*H$19 -> 175
B25: 13 | C25: =$B25*C$19 -> 52 | D25: =$B25*D$19 -> 78 | E25: =$B25*E$19 -> 104 | F25: =$B25*F$19 -> 130 | G25: =$B25*G$19 -> 156 | H25: =$B25*H$19 -> 182
B26: Green = exit value high enough for the target IRR from a $115B entry over the model hold (Returns!C9 × C4). Red = below the $115B entry price.
B29: 3. Dilution check: IRR (model hold) if the client's stake is diluted before exit
B30: Headline returns assume no dilution. FY25 AR: 2.8m options/RSUs outstanding vs ~59.6m shares in issue (incl. 11.0m H shares that convert above a hurdle price); press reports (FT) of a CEO share award worth up to ~10% at ~$150B.
B31: Dilution ↓ / Scenario → | C31: Bull | D31: Base | E31: Bear | F31: Expected | G31: CEO $200B
B32: 0 | C32: =('Returns '!$C$20/'Returns '!$C$4*(1-$B32))^(1/'Returns '!$C$6)-1 -> 0.27114982 | D32: =('Returns '!$C$21/'Returns '!$C$4*(1-$B32))^(1/'Returns '!$C$6)-1 -> 0.046931841 | E32: =('Returns '!$C$22/'Returns '!$C$4*(1-$B32))^(1/'Returns '!$C$6)-1 -> -0.22871276 | F32: =('Returns '!$C$23/'Returns '!$C$4*(1-$B32))^(1/'Returns '!$C$6)-1 -> 0.056318108 | G32: =('Returns '!$C$37/'Returns '!$C$4*(1-$B32))^(1/'Returns '!$C$6)-1 -> 0.24776518
B33: 0.03 | C33: =('Returns '!$C$20/'Returns '!$C$4*(1-$B33))^(1/'Returns '!$C$6)-1 -> 0.25575649 | D33: =('Returns '!$C$21/'Returns '!$C$4*(1-$B33))^(1/'Returns '!$C$6)-1 -> 0.034253745 | E33: =('Returns '!$C$22/'Returns '!$C$4*(1-$B33))^(1/'Returns '!$C$6)-1 -> -0.23805287 | F33: =('Returns '!$C$23/'Returns '!$C$4*(1-$B33))^(1/'Returns '!$C$6)-1 -> 0.043526347 | G33: =('Returns '!$C$37/'Returns '!$C$4*(1-$B33))^(1/'Returns '!$C$6)-1 -> 0.23265504
B34: 0.05 | C34: =('Returns '!$C$20/'Returns '!$C$4*(1-$B34))^(1/'Returns '!$C$6)-1 -> 0.24533496 | D34: =('Returns '!$C$21/'Returns '!$C$4*(1-$B34))^(1/'Returns '!$C$6)-1 -> 0.025670467 | E34: =('Returns '!$C$22/'Returns '!$C$4*(1-$B34))^(1/'Returns '!$C$6)-1 -> -0.24437627 | F34: =('Returns '!$C$23/'Returns '!$C$4*(1-$B34))^(1/'Returns '!$C$6)-1 -> 0.034866115 | G34: =('Returns '!$C$37/'Returns '!$C$4*(1-$B34))^(1/'Returns '!$C$6)-1 -> 0.22242523
B35: 0.1 | C35: =('Returns '!$C$20/'Returns '!$C$4*(1-$B35))^(1/'Returns '!$C$6)-1 -> 0.21869139 | D35: =('Returns '!$C$21/'Returns '!$C$4*(1-$B35))^(1/'Returns '!$C$6)-1 -> 0.0037265503 | E35: =('Returns '!$C$22/'Returns '!$C$4*(1-$B35))^(1/'Returns '!$C$6)-1 -> -0.26054262 | F35: =('Returns '!$C$23/'Returns '!$C$4*(1-$B35))^(1/'Returns '!$C$6)-1 -> 0.012725461 | G35: =('Returns '!$C$37/'Returns '!$C$4*(1-$B35))^(1/'Returns '!$C$6)-1 -> 0.1962718

Sheet IPO Comps
B1: Recent fintech IPOs: what they priced at and where they trade now
B2: Market data: StockAnalysis, close of 16 Oct 2026. IPO price and valuation: pricing announcements and press coverage
B4: Company | C4: Ticker | D4: IPO date | E4: IPO price ($) | F4: Valuation at IPO ($bn) | G4: Price 16 Oct 2026 ($) | H4: Share price vs IPO | I4: Market cap 16 Oct 2026 ($bn) | J4: Market cap vs IPO valuation | K4: Trailing P/S | L4: Forward P/S | M4: Source
B5: eToro | C5: ETOR | D5: 45791 | E5: 52 | F5: 4.2 | G5: 24.39 | H5: =G5/E5-1 -> -0.53096154 | I5: 1.94 | J5: =I5/F5-1 -> -0.53809524 | K5: 0.16 | L5: 2.13 | M5: IPO pricing coverage
B6: Chime | C6: CHYM | D6: 45820 | E6: 27 | F6: 11.6 | G6: 29.67 | H6: =G6/E6-1 -> 0.098888889 | I6: 11.23 | J6: =I6/F6-1 -> -0.031896552 | K6: 4.57 | L6: 3.67 | M6: IPO pricing coverage
B7: Klarna | C7: KLAR | D7: 45910 | E7: 40 | F7: 15.2 | G7: 13.02 | H7: =G7/E7-1 -> -0.6745 | I7: 4.94 | J7: =I7/F7-1 -> -0.675 | K7: 1.22 | L7: 1.15 | M7: IPO pricing coverage
B8: Average | H8: =AVERAGE(H5:H7) -> -0.36885755 | J8: =AVERAGE(J5:J7) -> -0.41499726
B9: Median | H9: =MEDIAN(H5:H7) -> -0.53096154 | J9: =MEDIAN(J5:J7) -> -0.53809524 | K9: =MEDIAN(K5:K7) -> 1.22 | L9: =MEDIAN(L5:L7) -> 2.13
B11: Revolut at the July 2026 secondary | F11: ='Returns '!C4 -> 115 | K11: =Peers!H11 -> 19.292659 | L11: =Peers!I11 -> 12.777778
B13: What this tells the committee
B14: • Two of the three trade 50–70% below their IPO price; only Chime is above it. Strong after-market demand is not guaranteed for fintech listings.
B15: • Even Chime, the best performer, trades on ~4.6x trailing sales — a quarter of the ~19x Revolut is priced at today.
B16: • Supports the WS4 risk "valuation compression at IPO" and argues against assuming Revolut keeps today's multiple through an IPO (the model bull case does).

Sheet Funding Timeline
B1: Revolut funding and valuation timeline
B4: Date | C4: Event | D4: Type | E4: Valuation ($bn) | F4: Size ($m) | G4: Lead / key investors or detail | H4: Step-up vs previous | I4: Last reported FY revenue ($bn) | J4: Valuation ÷ last FY revenue | K4: Source
B5: 43215 | C5: Series C | D5: Primary | E5: 1.7 | F5: 250 | G5: DST Global (lead); Index Ventures, Ribbit Capital | K5: TechCrunch, 25 Apr 2018
B6: 43885 | C6: Series D | D6: Primary | E6: 5.5 | F6: 500 | G6: TCV (lead) | H6: =E6/E5-1 -> 2.2352941 | K6: CNBC, 24 Feb 2020
B7: 44392 | C7: Series E | D7: Primary | E7: 33 | F7: 800 | G7: SoftBank Vision Fund 2, Tiger Global | H7: =E7/E6-1 -> 5 | K7: FY22 annual report (investors section); Global Venturing
B8: 45505 | C8: Secondary share sale | D8: Secondary | E8: 45 | F8: n/d | G8: New investors incl. Coatue, Durable, Dragoneer, Fidelity, Baillie Gifford, Goldman Sachs Alternatives, D1, Mubadala, Affinity Partners | H8: =E8/E7-1 -> 0.36363636 | I8: ='Financial Summary '!D20/10^6 -> 2.2293836 | J8: =E8/I8 -> 20.184952 | K8: FY24 annual report (CFO letter)
B9: 45985 | C9: Fundraise (secondary sale + new shares) | D9: Mixed | E9: 75 | F9: n/d | G9: Led by Coatue, Greenoaks, Dragoneer, Fidelity; with a16z, Franklin Templeton, T. Rowe Price, NVentures (Nvidia) | H9: =E9/E8-1 -> 0.66666667 | I9: ='Financial Summary '!E20/10^6 -> 3.955255 | J9: =E9/I9 -> 18.962115 | K9: FY25 annual report pp.14, 151, 198
B10: 46225 | C10: Company-run secondary sale | D10: Secondary | E10: 115 | F10: n/d | G10: ~$2,017 per share; buyers not disclosed | H10: =E10/E9-1 -> 0.53333333 | I10: ='Financial Summary '!F20/10^6 -> 5.9608164 | J10: =E10/I10 -> 19.292659 | K10: Tech.eu, 22 Jul 2026
B11: 46310 | C11: Forge Global price mark (not a transaction) | D11: Market mark | E11: 121.2 | F11: n/a | G11: $2,125 per share on the Forge secondary marketplace | H11: =E11/E10-1 -> 0.053913043 | I11: ='Financial Summary '!F20/10^6 -> 5.9608164 | J11: =E11/I11 -> 20.332785 | K11: Startup Fortune, 18 Oct 2026
B13: Annualised valuation growth, Jul 2021 → Jul 2026 | H13: =(E10/E7)^(1/YEARFRAC(B7,B10))-1 -> 0.28237994
B14: IPO target, FT Apr 2026 ($bn, low / high) | E14: 150 | F14: 200
B15: Step-up needed from $115B to IPO target | E15: =E14/E10-1 -> 0.30434783 | F15: =F14/E10-1 -> 0.73913043
B17: Reading the table
B18: • Since 2024 each mark has priced Revolut at roughly 19–20x its last reported annual revenue (column J): the valuation has risen because revenue has, not because the multiple expanded.
B19: • Our $15M would be bought at a price that has risen ~53% in eight months ($75B → $115B); the IPO target needs a further 30–74% on top.

Sheet Guidance Check
B1: FY2026 guidance check: what has to be true for $9B revenue
B3: A. Revenue
B4: FY26 guidance revenue ($ thousands) | C4: ='Financial Summary '!G20 -> 9000000
B5: FX rate used for FY26 (USD per GBP) | C5: ='Financial Summary '!G5 -> 1.32
B6: Implied FY26 revenue growth | C6: ='Financial Summary '!G10 -> 0.50986029
B7: FY25 actual revenue growth | C7: ='Financial Summary '!F10 -> 0.4613939
B8: FY25 interest income growth | C8: ='Financial Summary '!F33 -> 0.23273816
B9: FY26 guided PBT margin ($3.5B ÷ $9.0B) | C9: ='Financial Summary '!G23 -> 0.38888889
B10: FY25 actual PBT margin | C10: ='Financial Summary '!F14 -> 0.37939776
B12: B. Customers
B13: Retail customers, end FY24 (m) | C13: ='Financial Summary '!E30 -> 52.5
B14: Retail customers, end FY25 (m) | C14: ='Financial Summary '!F30 -> 68.3
B15: Retail customers, Jul 2026 (m, reported "over 75m") | C15: 75
B16: Retail customers, end FY26 (m) — assumption | C16: 85
B17: Average customers FY25 (m) | C17: =AVERAGE(C13,C14) -> 60.4
B18: Average customers FY26 (m) | C18: =AVERAGE(C14,C16) -> 76.65
B19: Average customer growth FY26 | C19: =C18/C17-1 -> 0.26903974
B21: C. What the guidance requires
B22: Revenue per customer growth REQUIRED in FY26 | C22: =(1+C6)/(1+C19)-1 -> 0.18976597
B23: Revenue per customer growth ACHIEVED in FY25 | C23: ='Financial Summary '!F32 -> 0.094835664
B24: Required ÷ achieved | C24: =C22/C23 -> 2.000998
B26: D. Sensitivity: end-FY26 customers
B27: End-FY26 retail customers (m) | C27: Average customer growth FY26 | D27: Revenue per customer growth required
B28: 80 | C28: =AVERAGE($C$14,B28)/$C$17-1 -> 0.22764901 | D28: =(1+$C$6)/(1+C28)-1 -> 0.22987946
B29: 85 | C29: =AVERAGE($C$14,B29)/$C$17-1 -> 0.26903974 | D29: =(1+$C$6)/(1+C29)-1 -> 0.18976597
B30: 90 | C30: =AVERAGE($C$14,B30)/$C$17-1 -> 0.31043046 | D30: =(1+$C$6)/(1+C30)-1 -> 0.1521865
B31: 95 | C31: =AVERAGE($C$14,B31)/$C$17-1 -> 0.35182119 | D31: =(1+$C$6)/(1+C31)-1 -> 0.11690829
B33: Notes
B34: • Guidance implies growth re-accelerates (FY25 +46% → FY26 ~+51%) while interest income, ~22% of revenue, grew only ~23% in FY25 as rates fell.
B35: • Unless customers grow much faster than in 2025, revenue per customer must rise roughly twice as fast as it did in FY25 (C24).
B36: • Group H1 2026 results are not public. Quarterly figures on data sites (e.g. Q1 2026, in EUR) cover Revolut Bank UAB only — not the group.
B37: • Source of $9B / $3.5B: Storonsky interview (Dec 2025), reported by Connecting the Dots in FinTech; it does not say whether $3.5B is pretax.
